{"data_tables":{},"disk_size":0,"data_size":0,"index_size":0,"disk_format_version":0,"committed_update_seq":0,"update_seq":0,"purge_seq":0,"compact_running":false,"doc_count":1239114,"doc_del_count":316,"doc_version_count":12185967,"user_count":437077,"store_engine":"mysql","sync_status":0,"need_sync_num":77,"success_sync_num":76,"fail_sync_num":1,"left_sync_num":0,"last_sync_time":1582608742420,"last_exist_sync_time":0,"last_sync_module":"@things-factory/integration-base","download":{"today":15660536,"thisweek":58718745,"thismonth":770665979,"lastday":43058209,"lastweek":246430245,"lastmonth":759640732},"db_name":"registry","instance_start_time":"1578913270538","node_version":"v12.8.1","app_version":"3.0.0-rc.31","donate":"https://www.gittip.com/fengmk2","sync_model":"all","cache_time":1582609336915}